django_easywebpack-0.2.1.dist-info/METADATA
django_easywebpack-0.2.1.dist-info/RECORD
django_easywebpack-0.2.1.dist-info/WHEEL
django_easywebpack-0.2.1.dist-info/top_level.txt
easywebpack/__init__.py
easywebpack/apps.py
easywebpack/webpack.py
easywebpack/management/__init__.py
easywebpack/management/commands/__init__.py
easywebpack/management/commands/collectstatic.py
easywebpack/management/commands/runserver.py
easywebpack/management/commands/webpack.py
easywebpack/templates/easywebpack/webpack_include.html
easywebpack/templatetags/__init__.py
easywebpack/templatetags/webpack_extras.py
easywebpack/tests/__init__.py
easywebpack/tests/test_templates.py
easywebpack/tests/test_webpack.py
easywebpack/tests/commands/test_collectstatic.py
easywebpack/tests/commands/test_runserver.py
easywebpack/tests/commands/test_webpack.py
