Metadata-Version: 2.1
Name: django-easywebpack
Version: 0.2.1
Summary: Making Django and Webpack best friends
Home-page: https://github.com/fndrz/django-easywebpack
Author: Fndrz
Author-email: django-easywebpack@fndrz.com
License: MIT
Project-URL: Documentation, https://django-easywebpack.readthedocs.io
Keywords: webpack static
Platform: UNKNOWN
Classifier: Development Status :: 3 - Alpha
Classifier: Environment :: Web Environment
Classifier: Framework :: Django :: 1.11
Classifier: Framework :: Django :: 2.0
Classifier: Intended Audience :: Developers
Classifier: License :: OSI Approved :: MIT License
Classifier: Natural Language :: English
Classifier: Operating System :: OS Independent
Classifier: Programming Language :: Python :: 2
Classifier: Programming Language :: Python :: 2.7
Classifier: Programming Language :: Python :: 3
Classifier: Programming Language :: Python :: 3.4
Classifier: Programming Language :: Python :: 3.5
Classifier: Programming Language :: Python :: 3.6
